setup.cfg
setup.py
bankpassweb/__init__.py
bankpassweb/apirequests.py
bankpassweb/apiresults.py
bankpassweb/bpwexceptions.py
bankpassweb/cards.py
bankpassweb/datatypes.py
bankpassweb/engine.py
bankpassweb/local_settings.py
bankpassweb/local_settings.py.example
bankpassweb/settings.py
bankpassweb/test.py
bankpassweb/webresults.py
bankpassweb/xmltramp.py
bankpassweb/satchmo_payment/__init__.py
bankpassweb/satchmo_payment/config.py
bankpassweb/satchmo_payment/processor.py
bankpassweb/satchmo_payment/urls.py
bankpassweb/satchmo_payment/views.py
bankpassweb/satchmo_payment/templates/checkout/bankpassweb/confirm.html
py_bankpassweb.egg-info/PKG-INFO
py_bankpassweb.egg-info/SOURCES.txt
py_bankpassweb.egg-info/dependency_links.txt
py_bankpassweb.egg-info/top_level.txt
