Metadata-Version: 1.0
Name: py-bankpassweb
Version: 0.1dev-r11
Summary: A Python interface to the BankPass Web e-commerce system
Home-page: http://code.google.com/p/py-bankpassweb
Author: Emanuele Pucciarelli
Author-email: ep@acm.org
License: GPL
Keywords: bankpass
Platform: UNKNOWN
